dissect/archive/__init__.py
dissect/archive/c_vbk.py
dissect/archive/c_vma.py
dissect/archive/c_wim.py
dissect/archive/exceptions.py
dissect/archive/vbk.py
dissect/archive/vma.py
dissect/archive/wim.py
dissect/archive/xva.py
dissect/archive/tools/__init__.py
dissect/archive/tools/backup.py
dissect_archive-1.7.dist-info/licenses/COPYRIGHT
dissect_archive-1.7.dist-info/licenses/LICENSE
dissect_archive-1.7.dist-info/METADATA
dissect_archive-1.7.dist-info/WHEEL
dissect_archive-1.7.dist-info/entry_points.txt
dissect_archive-1.7.dist-info/top_level.txt
dissect_archive-1.7.dist-info/RECORD
